imsosorrybutinc-0.7.1.dist-info/RECORD
imsosorrybutinc-0.7.1.dist-info/WHEEL
imsosorrybutinc-0.7.1.dist-info/top_level.txt
imsosorrybutinc-0.7.1.dist-info/METADATA
imsosorrybutinc-0.7.1.dist-info/licenses/LICENSE
uwuifier/_uwuifier.c
uwuifier/_uwuifier.pyi
uwuifier/__init__.py
uwuifier/py.typed
uwuifier/_uwuifier.cpython-312-darwin.so
