Metadata-Version: 2.4
Name: imsosorrybutinc
Version: 0.7.1
Summary: Sometimes it can be necessary to call upon the ancient arts... but in C!
Author-email: Bradley Reynolds <bradley.reynolds@tailstory.dev>
License-Expression: MIT
Project-URL: repository, https://github.com/letsbuilda/imsosorrybutinc/
Project-URL: documentation, https://docs.letsbuilda.dev/imsosorrybutinc/
Requires-Python: <3.15,>=3.10
License-File: LICENSE
Provides-Extra: dev
Requires-Dist: pip-tools; extra == "dev"
Requires-Dist: pre-commit; extra == "dev"
Requires-Dist: ruff; extra == "dev"
Requires-Dist: mypy; extra == "dev"
Provides-Extra: tests
Requires-Dist: pytest; extra == "tests"
Requires-Dist: pytest-randomly; extra == "tests"
Provides-Extra: docs
Requires-Dist: sphinx; extra == "docs"
Requires-Dist: furo; extra == "docs"
Requires-Dist: sphinx-autoapi; extra == "docs"
Requires-Dist: releases; extra == "docs"
Dynamic: license-file
